setup.py
dsnd_probability_oz/Binomialdistribution.py
dsnd_probability_oz/Gaussiandistribution.py
dsnd_probability_oz/Generaldistribution.py
dsnd_probability_oz/__init__.py
dsnd_probability_oz.egg-info/PKG-INFO
dsnd_probability_oz.egg-info/SOURCES.txt
dsnd_probability_oz.egg-info/dependency_links.txt
dsnd_probability_oz.egg-info/not-zip-safe
dsnd_probability_oz.egg-info/top_level.txt