Metadata-Version: 1.0
Name: dsnd-probability-oz
Version: 0.1
Summary: Gaussian and Binomial distributions
Home-page: UNKNOWN
Author: Ozzy Campos
Author-email: ozzycampos@yahoo.com
License: UNKNOWN
Platform: UNKNOWN
